activity/__init__.py
activity/admin.py
activity/logic.py
activity/models.py
activity/querysets.py
activity/views.py
activity/migrations/0001_initial.py
activity/migrations/__init__.py
django_simple_activity-1.1.0.dist-info/DESCRIPTION.rst
django_simple_activity-1.1.0.dist-info/METADATA
django_simple_activity-1.1.0.dist-info/RECORD
django_simple_activity-1.1.0.dist-info/WHEEL
django_simple_activity-1.1.0.dist-info/metadata.json
django_simple_activity-1.1.0.dist-info/top_level.txt
django_simple_activity-1.1.0.dist-info/zip-safe
