Metadata-Version: 2.0
Name: django-simple-activity
Version: 1.1.0
Summary: Simple, generic, activity streams from the actions on your site.
Home-page: https://github.com/richardasaurus/django-simple-activity
Author: Richard O'Dwyer
Author-email: richard@richard.do
License: Apache 2.0
Platform: UNKNOWN
Requires-Dist: django (>=1.10.0)
Requires-Dist: wheel
